<?xml version="1.0" encoding="UTF-8"?>
<!DOCTYPE ejb-jar PUBLIC "-//Sun Microsystems, Inc.//DTD Enterprise JavaBeans 1.1//EN" "http://java.sun.com/j2ee/dtds/ejb-jar_1_1.dtd">
   <ejb-jar id="ejb-jar_ID">
      <description>Generated by Export Tool for Enterprise Java Beans 1.1 version 1.0 from IBM VisualAge for Java version 4.0.</description>
      <display-name>JulyTrailcom</display-name>
      <enterprise-beans>
         <entity id="AddressInfo">
            <ejb-name>AddressInfo</ejb-name>
            <home>com.hps.july.trailcom.beans.AddressInfoHome</home>
            <remote>com.hps.july.trailcom.beans.AddressInfo</remote>
            <ejb-class>com.hps.july.trailcom.beans.AddressInfoBean</ejb-class>
            <persistence-type>Container</persistence-type>
            <prim-key-class>com.hps.july.trailcom.beans.AddressInfoKey</prim-key-class>
            <reentrant>False</reentrant>
            <cmp-field id="AddressInfo_startaddress">
               <field-name>startaddress</field-name>
            </cmp-field>
            <cmp-field id="AddressInfo_typeport">
               <field-name>typeport</field-name>
            </cmp-field>
            <cmp-field id="AddressInfo_e1count">
               <field-name>e1count</field-name>
            </cmp-field>
            <cmp-field id="AddressInfo_maxconnect">
               <field-name>maxconnect</field-name>
            </cmp-field>
            <cmp-field id="AddressInfo_lastaddress">
               <field-name>lastaddress</field-name>
            </cmp-field>
            <cmp-field id="AddressInfo_addressstep">
               <field-name>addressstep</field-name>
            </cmp-field>
            <cmp-field id="AddressInfo_resource">
               <field-name>resource</field-name>
            </cmp-field>
            <cmp-field id="AddressInfo_addresshead">
               <field-name>addresshead</field-name>
            </cmp-field>
            <cmp-field id="AddressInfo_addresstype">
               <field-name>addresstype</field-name>
            </cmp-field>
            <env-entry id="EnvEntry_1">
               <env-entry-name>ejb10-properties/AddressSpace</env-entry-name>
               <env-entry-type>java.lang.String</env-entry-type>
               <env-entry-value>com/hps/july/trailcom/beans/AddressSpace</env-entry-value>
            </env-entry>
            <env-entry id="EnvEntry_2">
               <env-entry-name>ejb10-properties/AddressInfo2</env-entry-name>
               <env-entry-type>java.lang.String</env-entry-type>
               <env-entry-value>com/hps/july/trailcom/beans/AddressInfo2</env-entry-value>
            </env-entry>
         </entity>
         <entity id="AddressInfo2">
            <ejb-name>AddressInfo2</ejb-name>
            <home>com.hps.july.trailcom.beans.AddressInfo2Home</home>
            <remote>com.hps.july.trailcom.beans.AddressInfo2</remote>
            <ejb-class>com.hps.july.trailcom.beans.AddressInfo2Bean</ejb-class>
            <persistence-type>Container</persistence-type>
            <prim-key-class>com.hps.july.trailcom.beans.AddressInfo2Key</prim-key-class>
            <reentrant>False</reentrant>
            <cmp-field id="AddressInfo2_addressportid">
               <field-name>addressportid</field-name>
            </cmp-field>
            <cmp-field id="AddressInfo2_addressname">
               <field-name>addressname</field-name>
            </cmp-field>
            <cmp-field id="AddressInfo2_addressinfo_resource">
               <field-name>addressinfo_resource</field-name>
            </cmp-field>
            <cmp-field id="AddressInfo2_addressinfo_typeport">
               <field-name>addressinfo_typeport</field-name>
            </cmp-field>
            <env-entry id="EnvEntry_3">
               <env-entry-name>ejb10-properties/AddressInfo</env-entry-name>
               <env-entry-type>java.lang.String</env-entry-type>
               <env-entry-value>com/hps/july/trailcom/beans/AddressInfo</env-entry-value>
            </env-entry>
         </entity>
         <entity id="AddressSpace">
            <ejb-name>AddressSpace</ejb-name>
            <home>com.hps.july.trailcom.beans.AddressSpaceHome</home>
            <remote>com.hps.july.trailcom.beans.AddressSpace</remote>
            <ejb-class>com.hps.july.trailcom.beans.AddressSpaceBean</ejb-class>
            <persistence-type>Container</persistence-type>
            <prim-key-class>com.hps.july.trailcom.beans.AddressSpaceKey</prim-key-class>
            <reentrant>False</reentrant>
            <cmp-field id="AddressSpace_address">
               <field-name>address</field-name>
            </cmp-field>
            <cmp-field id="AddressSpace_disabletime">
               <field-name>disabletime</field-name>
            </cmp-field>
            <cmp-field id="AddressSpace_storagecard">
               <field-name>storagecard</field-name>
            </cmp-field>
            <cmp-field id="AddressSpace_activestate">
               <field-name>activestate</field-name>
            </cmp-field>
            <cmp-field id="AddressSpace_portid">
               <field-name>portid</field-name>
            </cmp-field>
            <cmp-field id="AddressSpace_existstate">
               <field-name>existstate</field-name>
            </cmp-field>
            <cmp-field id="AddressSpace_realconnect">
               <field-name>realconnect</field-name>
            </cmp-field>
            <cmp-field id="AddressSpace_insegment">
               <field-name>insegment</field-name>
            </cmp-field>
            <cmp-field id="AddressSpace_addressinfo_resource">
               <field-name>addressinfo_resource</field-name>
            </cmp-field>
            <cmp-field id="AddressSpace_addressinfo_typeport">
               <field-name>addressinfo_typeport</field-name>
            </cmp-field>
            <env-entry id="EnvEntry_4">
               <env-entry-name>ejb10-properties/AddressInfo</env-entry-name>
               <env-entry-type>java.lang.String</env-entry-type>
               <env-entry-value>com/hps/july/trailcom/beans/AddressInfo</env-entry-value>
            </env-entry>
         </entity>
         <entity id="Hop">
            <ejb-name>Hop</ejb-name>
            <home>com.hps.july.trailcom.beans.HopHome</home>
            <remote>com.hps.july.trailcom.beans.Hop</remote>
            <ejb-class>com.hps.july.trailcom.beans.HopBean</ejb-class>
            <persistence-type>Container</persistence-type>
            <prim-key-class>com.hps.july.trailcom.beans.HopKey</prim-key-class>
            <reentrant>False</reentrant>
            <cmp-field id="Hop_modifiedby">
               <field-name>modifiedby</field-name>
            </cmp-field>
            <cmp-field id="Hop_lease_info">
               <field-name>lease_info</field-name>
            </cmp-field>
            <cmp-field id="Hop_siteid_endb">
               <field-name>siteid_endb</field-name>
            </cmp-field>
            <cmp-field id="Hop_expindate">
               <field-name>expindate</field-name>
            </cmp-field>
            <cmp-field id="Hop_siteid_enda">
               <field-name>siteid_enda</field-name>
            </cmp-field>
            <cmp-field id="Hop_createdby">
               <field-name>createdby</field-name>
            </cmp-field>
            <cmp-field id="Hop_abis_number">
               <field-name>abis_number</field-name>
            </cmp-field>
            <cmp-field id="Hop_hopsid">
               <field-name>hopsid</field-name>
            </cmp-field>
            <cmp-field id="Hop_speed">
               <field-name>speed</field-name>
            </cmp-field>
            <cmp-field id="Hop_beenetid">
               <field-name>beenetid</field-name>
            </cmp-field>
            <cmp-field id="Hop_modified">
               <field-name>modified</field-name>
            </cmp-field>
            <cmp-field id="Hop_created">
               <field-name>created</field-name>
            </cmp-field>
            <cmp-field id="Hop_rezerv">
               <field-name>rezerv</field-name>
            </cmp-field>
            <cmp-field id="Hop_expoutdate">
               <field-name>expoutdate</field-name>
            </cmp-field>
            <cmp-field id="Hop_equipmentid_enda">
               <field-name>equipmentid_enda</field-name>
            </cmp-field>
            <cmp-field id="Hop_permstatus">
               <field-name>permstatus</field-name>
            </cmp-field>
            <cmp-field id="Hop_hopstate">
               <field-name>hopstate</field-name>
            </cmp-field>
            <cmp-field id="Hop_equipmentid_endb">
               <field-name>equipmentid_endb</field-name>
            </cmp-field>
            <cmp-field id="Hop_hopstype">
               <field-name>hopstype</field-name>
            </cmp-field>
            <env-entry id="EnvEntry_5">
               <env-entry-name>ejb10-properties/RRLHops2</env-entry-name>
               <env-entry-type>java.lang.String</env-entry-type>
               <env-entry-value>com/hps/july/trailcom/beans/RRLHops2</env-entry-value>
            </env-entry>
            <env-entry id="EnvEntry_6">
               <env-entry-name>ejb10-properties/Sitedoc2Hops</env-entry-name>
               <env-entry-type>java.lang.String</env-entry-type>
               <env-entry-value>com/hps/july/trailcom/beans/Sitedoc2Hops</env-entry-value>
            </env-entry>
            <env-entry id="EnvEntry_7">
               <env-entry-name>ejb10-properties/HopLabel</env-entry-name>
               <env-entry-type>java.lang.String</env-entry-type>
               <env-entry-value>com/hps/july/trailcom/beans/HopLabel</env-entry-value>
            </env-entry>
            <env-entry id="EnvEntry_8">
               <env-entry-name>ejb10-properties/OpticalHop</env-entry-name>
               <env-entry-type>java.lang.String</env-entry-type>
               <env-entry-value>com/hps/july/trailcom/beans/OpticalHop</env-entry-value>
            </env-entry>
         </entity>
         <entity id="HopLabel">
            <ejb-name>HopLabel</ejb-name>
            <home>com.hps.july.trailcom.beans.HopLabelHome</home>
            <remote>com.hps.july.trailcom.beans.HopLabel</remote>
            <ejb-class>com.hps.july.trailcom.beans.HopLabelBean</ejb-class>
            <persistence-type>Container</persistence-type>
            <prim-key-class>com.hps.july.trailcom.beans.HopLabelKey</prim-key-class>
            <reentrant>False</reentrant>
            <cmp-field id="HopLabel_hopsnamecomments">
               <field-name>hopsnamecomments</field-name>
            </cmp-field>
            <cmp-field id="HopLabel_hopsname">
               <field-name>hopsname</field-name>
            </cmp-field>
            <cmp-field id="HopLabel_hopslabelid">
               <field-name>hopslabelid</field-name>
            </cmp-field>
            <cmp-field id="HopLabel_hopid_hopsid">
               <field-name>hopid_hopsid</field-name>
            </cmp-field>
            <env-entry id="EnvEntry_9">
               <env-entry-name>ejb10-properties/Hop</env-entry-name>
               <env-entry-type>java.lang.String</env-entry-type>
               <env-entry-value>com/hps/july/trailcom/beans/Hop</env-entry-value>
            </env-entry>
         </entity>
         <entity id="OpticalHop">
            <ejb-name>OpticalHop</ejb-name>
            <home>com.hps.july.trailcom.beans.OpticalHopHome</home>
            <remote>com.hps.july.trailcom.beans.OpticalHop</remote>
            <ejb-class>com.hps.july.trailcom.beans.OpticalHopBean</ejb-class>
            <persistence-type>Container</persistence-type>
            <prim-key-class>com.hps.july.trailcom.beans.OpticalHopKey</prim-key-class>
            <reentrant>False</reentrant>
            <cmp-field id="OpticalHop_hopscomment">
               <field-name>hopscomment</field-name>
            </cmp-field>
            <cmp-field id="OpticalHop_hopid_hopsid">
               <field-name>hopid_hopsid</field-name>
            </cmp-field>
            <env-entry id="EnvEntry_10">
               <env-entry-name>ejb10-properties/Hop</env-entry-name>
               <env-entry-type>java.lang.String</env-entry-type>
               <env-entry-value>com/hps/july/trailcom/beans/Hop</env-entry-value>
            </env-entry>
         </entity>
         <entity id="RRLHops2">
            <ejb-name>RRLHops2</ejb-name>
            <home>com.hps.july.trailcom.beans.RRLHops2Home</home>
            <remote>com.hps.july.trailcom.beans.RRLHops2</remote>
            <ejb-class>com.hps.july.trailcom.beans.RRLHops2Bean</ejb-class>
            <persistence-type>Container</persistence-type>
            <prim-key-class>com.hps.july.trailcom.beans.RRLHops2Key</prim-key-class>
            <reentrant>False</reentrant>
            <cmp-field id="RRLHops2_azimuthAB_Doc">
               <field-name>azimuthAB_Doc</field-name>
            </cmp-field>
            <cmp-field id="RRLHops2_cable_rrl_b">
               <field-name>cable_rrl_b</field-name>
            </cmp-field>
            <cmp-field id="RRLHops2_diam_b">
               <field-name>diam_b</field-name>
            </cmp-field>
            <cmp-field id="RRLHops2_cable_rrl_a">
               <field-name>cable_rrl_a</field-name>
            </cmp-field>
            <cmp-field id="RRLHops2_height_b_doc">
               <field-name>height_b_doc</field-name>
            </cmp-field>
            <cmp-field id="RRLHops2_file_number">
               <field-name>file_number</field-name>
            </cmp-field>
            <cmp-field id="RRLHops2_azimuth">
               <field-name>azimuth</field-name>
            </cmp-field>
            <cmp-field id="RRLHops2_cable_2mbr_b">
               <field-name>cable_2mbr_b</field-name>
            </cmp-field>
            <cmp-field id="RRLHops2_frequency_a2">
               <field-name>frequency_a2</field-name>
            </cmp-field>
            <cmp-field id="RRLHops2_frequency_b2">
               <field-name>frequency_b2</field-name>
            </cmp-field>
            <cmp-field id="RRLHops2_diam2_a">
               <field-name>diam2_a</field-name>
            </cmp-field>
            <cmp-field id="RRLHops2_comment_doc">
               <field-name>comment_doc</field-name>
            </cmp-field>
            <cmp-field id="RRLHops2_frequency_a_doc">
               <field-name>frequency_a_doc</field-name>
            </cmp-field>
            <cmp-field id="RRLHops2_type_hw">
               <field-name>type_hw</field-name>
            </cmp-field>
            <cmp-field id="RRLHops2_signal_calc_a">
               <field-name>signal_calc_a</field-name>
            </cmp-field>
            <cmp-field id="RRLHops2_diam_a_doc">
               <field-name>diam_a_doc</field-name>
            </cmp-field>
            <cmp-field id="RRLHops2_height_a">
               <field-name>height_a</field-name>
            </cmp-field>
            <cmp-field id="RRLHops2_cable_2mb_a">
               <field-name>cable_2mb_a</field-name>
            </cmp-field>
            <cmp-field id="RRLHops2_sfonumber">
               <field-name>sfonumber</field-name>
            </cmp-field>
            <cmp-field id="RRLHops2_diam_a">
               <field-name>diam_a</field-name>
            </cmp-field>
            <cmp-field id="RRLHops2_cable_power_a">
               <field-name>cable_power_a</field-name>
            </cmp-field>
            <cmp-field id="RRLHops2_power_a">
               <field-name>power_a</field-name>
            </cmp-field>
            <cmp-field id="RRLHops2_power_b">
               <field-name>power_b</field-name>
            </cmp-field>
            <cmp-field id="RRLHops2_signal_calc_b">
               <field-name>signal_calc_b</field-name>
            </cmp-field>
            <cmp-field id="RRLHops2_accumid_a">
               <field-name>accumid_a</field-name>
            </cmp-field>
            <cmp-field id="RRLHops2_number_in_file">
               <field-name>number_in_file</field-name>
            </cmp-field>
            <cmp-field id="RRLHops2_azimuthBA_Doc">
               <field-name>azimuthBA_Doc</field-name>
            </cmp-field>
            <cmp-field id="RRLHops2_comment_a">
               <field-name>comment_a</field-name>
            </cmp-field>
            <cmp-field id="RRLHops2_signal_real_b">
               <field-name>signal_real_b</field-name>
            </cmp-field>
            <cmp-field id="RRLHops2_power_doc">
               <field-name>power_doc</field-name>
            </cmp-field>
            <cmp-field id="RRLHops2_frequency_b_doc">
               <field-name>frequency_b_doc</field-name>
            </cmp-field>
            <cmp-field id="RRLHops2_frequency_a1">
               <field-name>frequency_a1</field-name>
            </cmp-field>
            <cmp-field id="RRLHops2_frequency_b1">
               <field-name>frequency_b1</field-name>
            </cmp-field>
            <cmp-field id="RRLHops2_diam_b_doc">
               <field-name>diam_b_doc</field-name>
            </cmp-field>
            <cmp-field id="RRLHops2_file_shortnumber">
               <field-name>file_shortnumber</field-name>
            </cmp-field>
            <cmp-field id="RRLHops2_capacity">
               <field-name>capacity</field-name>
            </cmp-field>
            <cmp-field id="RRLHops2_cable_power_b">
               <field-name>cable_power_b</field-name>
            </cmp-field>
            <cmp-field id="RRLHops2_comment_b">
               <field-name>comment_b</field-name>
            </cmp-field>
            <cmp-field id="RRLHops2_speed_doc">
               <field-name>speed_doc</field-name>
            </cmp-field>
            <cmp-field id="RRLHops2_accumid_b">
               <field-name>accumid_b</field-name>
            </cmp-field>
            <cmp-field id="RRLHops2_resource_doc">
               <field-name>resource_doc</field-name>
            </cmp-field>
            <cmp-field id="RRLHops2_diam2_b">
               <field-name>diam2_b</field-name>
            </cmp-field>
            <cmp-field id="RRLHops2_height_a_doc">
               <field-name>height_a_doc</field-name>
            </cmp-field>
            <cmp-field id="RRLHops2_signal_real_a">
               <field-name>signal_real_a</field-name>
            </cmp-field>
            <cmp-field id="RRLHops2_height_b">
               <field-name>height_b</field-name>
            </cmp-field>
            <cmp-field id="RRLHops2_hopid_hopsid">
               <field-name>hopid_hopsid</field-name>
            </cmp-field>
            <env-entry id="EnvEntry_11">
               <env-entry-name>ejb10-properties/Hop</env-entry-name>
               <env-entry-type>java.lang.String</env-entry-type>
               <env-entry-value>com/hps/july/trailcom/beans/Hop</env-entry-value>
            </env-entry>
         </entity>
         <entity id="Sitedoc2Hops">
            <ejb-name>Sitedoc2Hops</ejb-name>
            <home>com.hps.july.trailcom.beans.Sitedoc2HopsHome</home>
            <remote>com.hps.july.trailcom.beans.Sitedoc2Hops</remote>
            <ejb-class>com.hps.july.trailcom.beans.Sitedoc2HopsBean</ejb-class>
            <persistence-type>Container</persistence-type>
            <prim-key-class>com.hps.july.trailcom.beans.Sitedoc2HopsKey</prim-key-class>
            <reentrant>False</reentrant>
            <cmp-field id="Sitedoc2Hops_sitedoc">
               <field-name>sitedoc</field-name>
            </cmp-field>
            <cmp-field id="Sitedoc2Hops_hop_hopsid">
               <field-name>hop_hopsid</field-name>
            </cmp-field>
            <env-entry id="EnvEntry_12">
               <env-entry-name>ejb10-properties/Hop</env-entry-name>
               <env-entry-type>java.lang.String</env-entry-type>
               <env-entry-value>com/hps/july/trailcom/beans/Hop</env-entry-value>
            </env-entry>
         </entity>
         <session id="TrailcomProcessor">
            <ejb-name>TrailcomProcessor</ejb-name>
            <home>com.hps.july.trailcom.beans.TrailcomProcessorHome</home>
            <remote>com.hps.july.trailcom.beans.TrailcomProcessor</remote>
            <ejb-class>com.hps.july.trailcom.beans.TrailcomProcessorBean</ejb-class>
            <session-type>Stateless</session-type>
            <transaction-type>Container</transaction-type>
         </session>
      </enterprise-beans>
      <assembly-descriptor id="AssemblyDescriptor_ID">
         <container-transaction id="MethodTransaction_1">
            <method id="MethodElement_1">
               <ejb-name>AddressInfo</ejb-name>
               <method-name>*</method-name>
            </method>
            <trans-attribute>Required</trans-attribute>
         </container-transaction>
         <container-transaction id="MethodTransaction_2">
            <method id="MethodElement_2">
               <ejb-name>AddressInfo2</ejb-name>
               <method-name>*</method-name>
            </method>
            <trans-attribute>Required</trans-attribute>
         </container-transaction>
         <container-transaction id="MethodTransaction_3">
            <method id="MethodElement_3">
               <ejb-name>AddressSpace</ejb-name>
               <method-name>*</method-name>
            </method>
            <trans-attribute>Required</trans-attribute>
         </container-transaction>
         <container-transaction id="MethodTransaction_4">
            <method id="MethodElement_4">
               <ejb-name>Hop</ejb-name>
               <method-name>*</method-name>
            </method>
            <trans-attribute>Required</trans-attribute>
         </container-transaction>
         <container-transaction id="MethodTransaction_5">
            <method id="MethodElement_5">
               <ejb-name>HopLabel</ejb-name>
               <method-name>*</method-name>
            </method>
            <trans-attribute>Required</trans-attribute>
         </container-transaction>
         <container-transaction id="MethodTransaction_6">
            <method id="MethodElement_6">
               <ejb-name>OpticalHop</ejb-name>
               <method-name>*</method-name>
            </method>
            <trans-attribute>Required</trans-attribute>
         </container-transaction>
         <container-transaction id="MethodTransaction_7">
            <method id="MethodElement_7">
               <ejb-name>RRLHops2</ejb-name>
               <method-name>*</method-name>
            </method>
            <trans-attribute>Required</trans-attribute>
         </container-transaction>
         <container-transaction id="MethodTransaction_8">
            <method id="MethodElement_8">
               <ejb-name>Sitedoc2Hops</ejb-name>
               <method-name>*</method-name>
            </method>
            <trans-attribute>Required</trans-attribute>
         </container-transaction>
         <container-transaction id="MethodTransaction_9">
            <method id="MethodElement_9">
               <ejb-name>TrailcomProcessor</ejb-name>
               <method-name>*</method-name>
            </method>
            <trans-attribute>Required</trans-attribute>
         </container-transaction>
      </assembly-descriptor>
   </ejb-jar>
